cave_utils/__init__.py
cave_utils/arguments.py
cave_utils/custom_coordinates.py
cave_utils/geo_utils.py
cave_utils/log.py
cave_utils/socket.py
cave_utils/api/__init__.py
cave_utils/api/appBar.py
cave_utils/api/extraKwargs.py
cave_utils/api/globalOutputs.py
cave_utils/api/groupedOutputs.py
cave_utils/api/mapFeatures.py
cave_utils/api/maps.py
cave_utils/api/pages.py
cave_utils/api/panes.py
cave_utils/api/settings.py
cave_utils/api_utils/__init__.py
cave_utils/api_utils/general.py
cave_utils/api_utils/validator.py
cave_utils/api_utils/validator_utils.py
cave_utils/builders/__init__.py
cave_utils/builders/groups.py
cave_utils-3.4.4.dist-info/licenses/LICENSE
cave_utils-3.4.4.dist-info/licenses/NOTICE.md
cave_utils-3.4.4.dist-info/METADATA
cave_utils-3.4.4.dist-info/WHEEL
cave_utils-3.4.4.dist-info/top_level.txt
cave_utils-3.4.4.dist-info/RECORD
