Metadata-Version: 2.4
Name: cave_utils
Version: 3.4.4
Summary: Python wrapper for api use in the cave_app
Author-email: Connor Makowski <conmak@mit.edu>
Project-URL: Homepage, https://github.com/mit-cave/cave_utils
Project-URL: Bug Tracker, https://github.com/mit-cave/cave_utils/issues
Classifier: Programming Language :: Python :: 3
Classifier: Operating System :: OS Independent
Requires-Python: >=3.11
License-File: LICENSE
License-File: NOTICE.md
Requires-Dist: pamda<3.0.0,>=2.8.0
Requires-Dist: type_enforced<3.0.0,>=2.2.0
Dynamic: license-file
